[
  {
    "tag_name": "entity",
    "ids_to_tags": {
      "1": "B-change_room_type",
      "2": "I-change_room_type",
      "3": "L-change_room_type",
      "4": "U-change_room_type",
      "5": "B-id_card",
      "6": "I-id_card",
      "7": "L-id_card",
      "8": "U-id_card",
      "9": "B-intend_time",
      "10": "I-intend_time",
      "11": "L-intend_time",
      "12": "U-intend_time",
      "13": "B-m_name",
      "14": "I-m_name",
      "15": "L-m_name",
      "16": "U-m_name",
      "17": "B-my_name",
      "18": "I-my_name",
      "19": "L-my_name",
      "20": "U-my_name",
      "21": "B-name",
      "22": "I-name",
      "23": "L-name",
      "24": "U-name",
      "25": "B-quantity",
      "26": "I-quantity",
      "27": "L-quantity",
      "28": "U-quantity",
      "29": "B-room_info",
      "30": "I-room_info",
      "31": "L-room_info",
      "32": "U-room_info",
      "33": "B-room_type",
      "34": "I-room_type",
      "35": "L-room_type",
      "36": "U-room_type",
      "0": "O"
    },
    "tags_to_ids": {
      "B-change_room_type": 1,
      "I-change_room_type": 2,
      "L-change_room_type": 3,
      "U-change_room_type": 4,
      "B-id_card": 5,
      "I-id_card": 6,
      "L-id_card": 7,
      "U-id_card": 8,
      "B-intend_time": 9,
      "I-intend_time": 10,
      "L-intend_time": 11,
      "U-intend_time": 12,
      "B-m_name": 13,
      "I-m_name": 14,
      "L-m_name": 15,
      "U-m_name": 16,
      "B-my_name": 17,
      "I-my_name": 18,
      "L-my_name": 19,
      "U-my_name": 20,
      "B-name": 21,
      "I-name": 22,
      "L-name": 23,
      "U-name": 24,
      "B-quantity": 25,
      "I-quantity": 26,
      "L-quantity": 27,
      "U-quantity": 28,
      "B-room_info": 29,
      "I-room_info": 30,
      "L-room_info": 31,
      "U-room_info": 32,
      "B-room_type": 33,
      "I-room_type": 34,
      "L-room_type": 35,
      "U-room_type": 36,
      "O": 0
    },
    "num_tags": 37
  },
  {
    "tag_name": "group",
    "ids_to_tags": {
      "1": "B-1",
      "2": "I-1",
      "3": "L-1",
      "4": "U-1",
      "5": "B-2",
      "6": "I-2",
      "7": "L-2",
      "8": "U-2",
      "0": "O"
    },
    "tags_to_ids": {
      "B-1": 1,
      "I-1": 2,
      "L-1": 3,
      "U-1": 4,
      "B-2": 5,
      "I-2": 6,
      "L-2": 7,
      "U-2": 8,
      "O": 0
    },
    "num_tags": 9
  }
]